{
    "fixture": "Heidenheim vs Dortmund",
    "head_to_head": {
        "teams": {
            "match_four": [
                "Heidenheim",
                "Dortmund"
            ]
        },
        "goals": {
            "match_four": [
                1,
                2
            ]
        },
        "x_goals": {
            "match_four": [
                0.58,
                2.41
            ]
        },
        "corners": {
            "match_four": [
                4,
                5
            ]
        },
        "fouls": {
            "match_four": [
                11,
                9
            ]
        },
        "HT_cards": {
            "match_four": [
                1,
                1
            ]
        },
        "FT_cards": {
            "match_four": [
                1,
                4
            ]
        }
    }
}