{
            
    "name": "Cagliari",
    "coach": "Davide Nicola",
    "team_logo": "https://bunmi2020.github.io/bnf_data/teams_icon/serie_a/cagliari.png",
    "playing_style": "Wide play; Long balls",
    "pressing_style": " ",
    "attacking_style": "High crossing frequency; Frequent through ball attempts; Attacking down the right; High shot volume",
    "defensive_style": "High Line; Use offside positioning",
    "goal_scored_pg": 1.05,
    "goals_concede_pg": 1.63,
    "aggressive_players": ["Zito Luvumbo", "Roberto Piccoli"],
    "provocative_players": ["Zito Luvumbo", "Roberto Piccoli", "Yerry Mina", "Nicolas Viola"],
    "unavailable_attacking_players": [],
    "win_form": ["D","W","L","L","W","D","W"],
    "corner_form": ["L","W","D","L","W","L","W"],
    "recent_matches": {
        "teams": {
            "match_3": [
                "Atalanta",
                "Cagliari"
            ],
            "match_4": [
                "Cagliari",
                "Parma"
            ],
            "match_5": [
                "Cagliari",
                "Lazio"
            ],
            "match_6": [
                "Torino",
                "Cagliari"
            ],
            "match_7": [
                "Cagliari",
                "Lecce"
            ],
            "match_1": [
                "AC Milan",
                "Cagliari"
            ],
            "match_2": [
                "Monza",
                "Cagliari"
            ]
        },
        "goals": {
            "match_3": [
                0,
                0
            ],
            "match_4": [
                2,
                1
            ],
            "match_5": [
                1,
                2
            ],
            "match_6": [
                2,
                0
            ],
            "match_7": [
                4,
                1
            ],
            "match_1": [
                1,
                1
            ],
            "match_2": [
                1,
                2
            ]
        },
        "x_goals": {
            "match_3": [
                0.42,
                0.16
            ],
            "match_4": [
                0.94,
                0.86
            ],
            "match_5": [
                1.49,
                1.29
            ],
            "match_6": [
                1.84,
                0.36
            ],
            "match_7": [
                2.74,
                0.5
            ],
            "match_1": [
                2.14,
                0.37
            ],
            "match_2": [
                1.58,
                0.69
            ]
        },
        "corners": {
            "match_3": [
                8,
                2
            ],
            "match_4": [
                7,
                6
            ],
            "match_5": [
                7,
                7
            ],
            "match_6": [
                6,
                3
            ],
            "match_7": [
                6,
                1
            ],
            "match_1": [
                9,
                1
            ],
            "match_2": [
                1,
                3
            ]
        },
        "fouls": {
            "match_3": [
                7,
                11
            ],
            "match_4": [
                14,
                12
            ],
            "match_5": [
                14,
                9
            ],
            "match_6": [
                11,
                10
            ],
            "match_7": [
                11,
                10
            ],
            "match_1": [
                9,
                11
            ],
            "match_2": [
                16,
                19
            ]
        },
        "HT_cards": {
            "match_3": [
                0,
                0
            ],
            "match_4": [
                0,
                0
            ],
            "match_5": [
                0,
                0
            ],
            "match_6": [
                0,
                0
            ],
            "match_7": [
                0,
                1
            ],
            "match_1": [
                0,
                1
            ],
            "match_2": [
                1,
                1
            ]
        },
        "FT_cards": {
            "match_3": [
                1,
                1
            ],
            "match_4": [
                0,
                2
            ],
            "match_5": [
                0,
                0
            ],
            "match_6": [
                0,
                1
            ],
            "match_7": [
                3,
                2
            ],
            "match_1": [
                1,
                2
            ],
            "match_2": [
                3,
                2
            ]
        }
    }
  }