{
        
    "name": "Everton",
    "coach": "Sean Dyche",
    "team_logo": "https://bunmi2020.github.io/bnf_data/teams_icon/PL/everton.png",
    "playing_style": "Wide play; Long balls",
    "pressing_style": "Mid-block",
    "attacking_style": "High crossing frequency; High shot volume; Attacking down the right; Take long shots",
    "defensive_style": "Compact",
    "aggressive_players": ["James Tarkowski","Abdoulaye Doucoure","James Garner"],
    "provocative_players": ["James Garner"],
    "unavailable_attacking_players": [],
    "recent_matches": {
        "teams": {
            "match_one": [
                "Everton",
                "Fulham"
            ],
            "match_two": [
                "Ipswich",
                "Everton"
            ],
            "match_three": [
                "Everton",
                "Newcastle"
            ],
            "match_four": [
                "Everton",
                "Crystal Palace"
            ],
            "match_five": [
                "Leicester",
                "Everton"
            ],
            "match_six": [
                "Aston Villa",
                "Everton"
            ],
            "match_seven": [
                "Everton",
                "Bournemouth"
            ]
        },
        "goals": {
            "match_one": [
                1,
                1
            ],
            "match_two": [
                0,
                2
            ],
            "match_three": [
                0,
                0
            ],
            "match_four": [
                2,
                1
            ],
            "match_five": [
                1,
                1
            ],
            "match_six": [
                3,
                2
            ],
            "match_seven": [
                2,
                3
            ]
        },
        "x_goals": {
            "match_one": [
                0.79,
                1.25
            ],
            "match_two": [
                1.27,
                1.74
            ],
            "match_three": [
                0.64,
                2.07
            ],
            "match_four": [
                1.15,
                0.89
            ],
            "match_five": [
                0.88,
                0.84
            ],
            "match_six": [
                2.23,
                0.75
            ],
            "match_seven": [
                1.77,
                2.44
            ]
        },
        "corners": {
            "match_one": [
                4,
                2
            ],
            "match_two": [
                5,
                7
            ],
            "match_three": [
                0,
                10
            ],
            "match_four": [
                5,
                8
            ],
            "match_five": [
                6,
                1
            ],
            "match_six": [
                6,
                2
            ],
            "match_seven": [
                8,
                4
            ]
        },
        "fouls": {
            "match_one": [
                8,
                8
            ],
            "match_two": [
                12,
                10
            ],
            "match_three": [
                12,
                8
            ],
            "match_four": [
                13,
                11
            ],
            "match_five": [
                11,
                12
            ],
            "match_six": [
                10,
                12
            ],
            "match_seven": [
                6,
                11
            ]
        },
        "HT_cards": {
            "match_one": [
                0,
                0
            ],
            "match_two": [
                0,
                1
            ],
            "match_three": [
                1,
                0
            ],
            "match_four": [
                0,
                0
            ],
            "match_five": [
                0,
                0
            ],
            "match_six": [
                0,
                2
            ],
            "match_seven": [
                0,
                0
            ]
        },
        "FT_cards": {
            "match_one": [
                1,
                0
            ],
            "match_two": [
                1,
                1
            ],
            "match_three": [
                1,
                2
            ],
            "match_four": [
                2,
                0
            ],
            "match_five": [
                1,
                2
            ],
            "match_six": [
                1,
                4
            ],
            "match_seven": [
                2,
                1
            ]
        }
    }
  }